genai/__init__.py
genai/_version.py
genai/context.py
genai/display.py
genai/generate.py
genai/magics.py
genai/prompts.py
genai/suggestions.py
genai/tokens.py
genai-2.0.0.dist-info/LICENSE
genai-2.0.0.dist-info/METADATA
genai-2.0.0.dist-info/WHEEL
genai-2.0.0.dist-info/RECORD
