Metadata-Version: 2.1
Name: genai
Version: 2.0.0
Summary: Generative AI for IPython (enhance your code cells)
License: BSD-3-Clause
Keywords: notebook,api,noteable,chatgpt,gpt3,openai,ipython,traceback,assist,llm
Author: Kyle Kelley
Author-email: rgbkrk@gmail.com
Maintainer: Kyle Kelley
Maintainer-email: rgbkrk@gmail.com
Requires-Python: >=3.8,<4.0
Classifier: Intended Audience :: Developers
Classifier: License :: OSI Approved :: BSD License
Classifier: Programming Language :: Python
Classifier: Programming Language :: Python :: 3
Classifier: Programming Language :: Python :: 3.8
Classifier: Programming Language :: Python :: 3.9
Classifier: Programming Language :: Python :: 3.10
Classifier: Programming Language :: Python :: 3.11
Classifier: Programming Language :: Python :: 3.10
Classifier: Programming Language :: Python :: 3.8
Classifier: Programming Language :: Python :: 3.9
Requires-Dist: ipython (>=8.10.0,<9.0.0)
Requires-Dist: openai (>=0.27.0,<0.28.0)
Requires-Dist: tabulate (>=0.9.0,<0.10.0)
Requires-Dist: tiktoken (>=0.3.2,<0.4.0)
Requires-Dist: vdom (>=0.6,<0.7)
